odoo/addons/l10n_et_payroll_FIT2016/README.rst
odoo/addons/l10n_et_payroll_FIT2016/__init__.py
odoo/addons/l10n_et_payroll_FIT2016/__manifest__.py
odoo/addons/l10n_et_payroll_FIT2016/data/payroll_data.xml
odoo/addons/l10n_et_payroll_FIT2016/readme/CREDITS.rst
odoo/addons/l10n_et_payroll_FIT2016/readme/DESCRIPTION.rst
odoo/addons/l10n_et_payroll_FIT2016/static/description/icon.png
odoo/addons/l10n_et_payroll_FIT2016/static/description/index.html
odoo/addons/l10n_et_payroll_FIT2016/static/src/img/main_screenshot.png
odoo14_addon_l10n_et_payroll_FIT2016-14.0.1.0.1.dev2.dist-info/METADATA
odoo14_addon_l10n_et_payroll_FIT2016-14.0.1.0.1.dev2.dist-info/WHEEL
odoo14_addon_l10n_et_payroll_FIT2016-14.0.1.0.1.dev2.dist-info/top_level.txt
odoo14_addon_l10n_et_payroll_FIT2016-14.0.1.0.1.dev2.dist-info/RECORD
