Metadata-Version: 2.1
Name: odoo14-addon-l10n_et_payroll_FIT2016
Version: 14.0.1.0.1.dev2
Summary: Ethiopian Federal Income Tax tables (rev. 2008)
Home-page: https://github.com/trevi-software/trevi-hr
Author: TREVI Software
License: AGPL-3
Classifier: Programming Language :: Python
Classifier: Framework :: Odoo
Classifier: Framework :: Odoo :: 14.0
Classifier: License :: OSI Approved :: GNU Affero General Public License v3
Requires-Python: >=3.6
Requires-Dist: odoo14-addon-l10n-et-payroll-category
Requires-Dist: odoo14-addon-payroll
Requires-Dist: odoo<14.1dev,>=14.0a
